{"997676": {"description": "wdadwf gaer ehr sjtey7 t6s r6h rsdfgbs ", "defendants": ["Test"], "charges": ["Awdaw daw"], "pleas": ["Not guilty"], "evidence": ["meowmeowI'macow"], "state": "open", "defense": 108986791696048128, "created_timestamp": 1664020306.021635, "type": "criminal"}, "181098": {"description": "daiunba wnuiawdnidw noiwauiu niunaf iuanwd ijwd naijn", "defendants": ["inini nigood"], "charges": ["Comma", "Separated", "Charges"], "pleas": ["Not guilty", "Not guilty", "Not guilty"], "evidence": ["all of it"], "state": "open", "defense": 108986791696048128, "created_timestamp": 1664020436.33833, "type": "criminal"}, "247676": {"description": "wdargs ekujn waoij ppwaokmgrpo imawoimk gr", "defendants": ["Testy"], "charges": ["Perjury", "Arson", "Murder"], "pleas": ["Not guilty", "Not guilty", "Not guilty"], "evidence": ["CCTV Footage"], "state": "open", "defense": 108986791696048128, "created_timestamp": 1664059018.860845, "type": "criminal"}, "177819": {"description": "awdkhb oidwaorg po fekm3klkfs eoi lakwlkndf sm,", "defendants": ["Testy McTest"], "charges": ["Murder", "Arson"], "pleas": ["Not guilty", "Not guilty"], "evidence": ["CCTV footage"], "state": "open", "defense": 108986791696048128, "created_timestamp": 1664059308.92138, "type": "criminal"}, "297117": {"description": "Alex Horne is an absolute little bitch who stole money from me.", "defendants": ["Alex Horne"], "state": "new", "plaintiff": "Greg Davies", "plaintiff_attorney": 108986791696048128, "created_timestamp": 1666980743.960804, "type": "Tort"}, "964141": {"description": "aadw", "defendants": ["adadw"], "state": "new", "plaintiff": "wawd", "plaintiff_attorney": 108986791696048128, "created_timestamp": 1666996074.003987, "contract_number": "45612", "type": "Contract"}, "754740": {"description": "awdadw", "defendants": ["awddwa"], "state": "new", "plaintiff": "adwdaw", "plaintiff_attorney": 108986791696048128, "created_timestamp": 1666996281.707509, "contract_number": "adwadw", "type": "Contract"}, "675425": {"description": "This is a description :D", "defendants": ["Test Name2"], "state": "validated", "plaintiff": "Test Name", "plaintiff_attorney": 194145496552570891, "created_timestamp": 1666999267.429848, "contract_number": "10101", "type": "Contract", "judge": 108986791696048128}, "506707": {"description": "Scammer get scammed", "defendants": ["Mike Cox Mall"], "state": "rejected", "plaintiff": "Hugh Janus", "plaintiff_attorney": 570988754026627092, "created_timestamp": 1667004047.826029, "contract_number": "12345", "type": "Contract", "judge": 108986791696048128}, "871415": {"description": "He didn't respect the contract clause #5", "defendants": ["John Garfield"], "state": "validated", "plaintiff": "Autumn Black", "plaintiff_attorney": 108986791696048128, "created_timestamp": 1667146496.42034, "contract_number": "45612", "type": "Contract", "judge": 108986791696048128}, "297152": {"description": "Defendants' failure to deliver on contractual obligations. Defendants' failure to register business as a Partnership and not as a Sole Proprietorship which the business is registered as. Defendants' failure to deliver on the return on investment owed to the plaintiff.", "defendants": ["Solomon Goldestein and Gold Interiors"], "state": "new", "plaintiff": "Percival Banks", "plaintiff_attorney": 747988746565320826, "created_timestamp": 1667670636.840696, "contract_number": "92838", "type": "Contract"}}